{
  "id": 51727,
  "url": "http://www.xxx.yyy.com",
  "publish_date": "21/11/2013 às 15:37",
  "ts": 1385055857222,
  "events": [
    {
      "created_at": "21/11/2013 às 15:44",
      "title": "xxx yyy zzz",
      "description": "kkk ppp",
      "last_update_date": "21/11/2013 às 15:37",
      "type": "Suggestion",
      "full_site_name": "Something",
      "image_url_original": "http://zzz.yy/a/b",
      "user": {
        "is_editor": false,
        "picture": "http://www.xxx.yyy/1",
        "name": "xxxx yyyy"
      },
      "group": {
        "id": 2,
        "name": "pppppp"
      }
    },
    {
      "created_at": "21/11/2013 às 15:44",
      "comment": "aaa",
      "type": "Comment",
      "user": {
        "is_editor": false,
        "picture": "http://www.xxx.yyy/2",
        "name": "xxxx yyyy"
      }
    },
    {
      "created_at": "21/11/2013 às 17:04",
      "status": "viewed",
      "pt_status": "visualizada",
      "type": "Status"
    },
    {
      "created_at": "21/11/2013 às 17:12",
      "comment": "bbbb",
      "type": "Comment",
      "user": {
        "is_editor": false,
        "picture": "http://www.xxx.yyy/3",
        "name": "xxxx yyyy"
      },
      "group": {
        "id": 2,
        "name": "pppppp"
      }
    },
    {
      "created_at": "21/11/2013 às 17:15",
      "status": "used",
      "pt_status": "destacada",
      "type": "Status"
    },
    {
      "created_at": "21/11/2013 às 17:21",
      "comment": "ccc",
      "type": "Comment",
      "user": {
        "is_editor": false,
        "picture": "http://www.xxx.yyy/4",
        "name": "kkkkkk"
      },
      "group": {
        "id": 2,
        "name": "pppppp"
      }
    },
    {
      "created_at": "21/11/2013 às 17:21",
      "comment": "ccc",
      "type": "Comment",
      "user": {
        "is_editor": false,
        "picture": "http://www.xxx.yyy/4",
        "name": "kkkkkk"
      },
      "group": {
        "id": 2,
        "name": "pppppp"
      }
    },
    {
      "created_at": "21/11/2013 às 17:21",
      "comment": "ccc",
      "type": "Comment",
      "user": {
        "is_editor": false,
        "picture": "http://www.xxx.yyy/4",
        "name": "kkkkkk"
      },
      "group": {
        "id": 2,
        "name": "pppppp"
      }
    },
    {
      "created_at": "21/11/2013 às 17:21",
      "comment": "ccc",
      "type": "Comment",
      "user": {
        "is_editor": false,
        "picture": "http://www.xxx.yyy/4",
        "name": "kkkkkk"
      },
      "group": {
        "id": 2,
        "name": "pppppp"
      }
    },
    {
      "created_at": "21/11/2013 às 17:21",
      "comment": "ccc",
      "type": "Comment",
      "user": {
        "is_editor": false,
        "picture": "http://www.xxx.yyy/4",
        "name": "kkkkkk"
      },
      "group": {
        "id": 2,
        "name": "pppppp"
      }
    },
    {
      "created_at": "21/11/2013 às 17:21",
      "comment": "ccc",
      "type": "Comment",
      "user": {
        "is_editor": false,
        "picture": "http://www.xxx.yyy/4",
        "name": "kkkkkk"
      },
      "group": {
        "id": 2,
        "name": "pppppp"
      }
    },
    {
      "created_at": "21/11/2013 às 17:21",
      "comment": "ccc",
      "type": "Comment",
      "user": {
        "is_editor": false,
        "picture": "http://www.xxx.yyy/4",
        "name": "kkkkkk"
      },
      "group": {
        "id": 2,
        "name": "pppppp"
      }
    },
    {
      "created_at": "21/11/2013 às 17:21",
      "comment": "ccc",
      "type": "Comment",
      "user": {
        "is_editor": false,
        "picture": "http://www.xxx.yyy/4",
        "name": "kkkkkk"
      },
      "group": {
        "id": 2,
        "name": "pppppp"
      }
    },
    {
      "created_at": "21/11/2013 às 17:21",
      "comment": "ccc",
      "type": "Comment",
      "user": {
        "is_editor": false,
        "picture": "http://www.xxx.yyy/4",
        "name": "kkkkkk"
      },
      "group": {
        "id": 2,
        "name": "pppppp"
      }
    },
    {
      "created_at": "21/11/2013 às 17:21",
      "comment": "ccc",
      "type": "Comment",
      "user": {
        "is_editor": false,
        "picture": "http://www.xxx.yyy/4",
        "name": "kkkkkk"
      },
      "group": {
        "id": 2,
        "name": "pppppp"
      }
    },
    {
      "created_at": "21/11/2013 às 17:21",
      "comment": "ccc",
      "type": "Comment",
      "user": {
        "is_editor": false,
        "picture": "http://www.xxx.yyy/4",
        "name": "kkkkkk"
      },
      "group": {
        "id": 2,
        "name": "pppppp"
      }
    },
    {
      "created_at": "21/11/2013 às 17:21",
      "comment": "ccc",
      "type": "Comment",
      "user": {
        "is_editor": false,
        "picture": "http://www.xxx.yyy/4",
        "name": "kkkkkk"
      },
      "group": {
        "id": 2,
        "name": "pppppp"
      }
    },
    {
      "created_at": "21/11/2013 às 17:21",
      "comment": "ccc",
      "type": "Comment",
      "user": {
        "is_editor": false,
        "picture": "http://www.xxx.yyy/4",
        "name": "kkkkkk"
      },
      "group": {
        "id": 2,
        "name": "pppppp"
      }
    },
    {
      "created_at": "21/11/2013 às 17:21",
      "comment": "ccc",
      "type": "Comment",
      "user": {
        "is_editor": false,
        "picture": "http://www.xxx.yyy/4",
        "name": "kkkkkk"
      },
      "group": {
        "id": 2,
        "name": "pppppp"
      }
    },
    {
      "created_at": "21/11/2013 às 17:21",
      "comment": "ccc",
      "type": "Comment",
      "user": {
        "is_editor": false,
        "picture": "http://www.xxx.yyy/4",
        "name": "kkkkkk"
      },
      "group": {
        "id": 2,
        "name": "pppppp"
      }
    },
    {
      "created_at": "21/11/2013 às 17:21",
      "comment": "ccc",
      "type": "Comment",
      "user": {
        "is_editor": false,
        "picture": "http://www.xxx.yyy/4",
        "name": "kkkkkk"
      },
      "group": {
        "id": 2,
        "name": "pppppp"
      }
    },
    {
      "created_at": "21/11/2013 às 17:21",
      "comment": "ccc",
      "type": "Comment",
      "user": {
        "is_editor": false,
        "picture": "http://www.xxx.yyy/4",
        "name": "kkkkkk"
      },
      "group": {
        "id": 2,
        "name": "pppppp"
      }
    },
    {
      "created_at": "21/11/2013 às 17:21",
      "comment": "ccc",
      "type": "Comment",
      "user": {
        "is_editor": false,
        "picture": "http://www.xxx.yyy/4",
        "name": "kkkkkk"
      },
      "group": {
        "id": 2,
        "name": "pppppp"
      }
    },
    {
      "created_at": "21/11/2013 às 17:21",
      "comment": "ccc",
      "type": "Comment",
      "user": {
        "is_editor": false,
        "picture": "http://www.xxx.yyy/4",
        "name": "kkkkkk"
      },
      "group": {
        "id": 2,
        "name": "pppppp"
      }
    },
    {
      "created_at": "21/11/2013 às 17:21",
      "comment": "ccc",
      "type": "Comment",
      "user": {
        "is_editor": false,
        "picture": "http://www.xxx.yyy/4",
        "name": "kkkkkk"
      },
      "group": {
        "id": 2,
        "name": "pppppp"
      }
    },
    {
      "created_at": "21/11/2013 às 17:21",
      "comment": "ccc",
      "type": "Comment",
      "user": {
        "is_editor": false,
        "picture": "http://www.xxx.yyy/4",
        "name": "kkkkkk"
      },
      "group": {
        "id": 2,
        "name": "pppppp"
      }
    },
    {
      "created_at": "21/11/2013 às 17:21",
      "comment": "ccc",
      "type": "Comment",
      "user": {
        "is_editor": false,
        "picture": "http://www.xxx.yyy/4",
        "name": "kkkkkk"
      },
      "group": {
        "id": 2,
        "name": "pppppp"
      }
    },
    {
      "created_at": "21/11/2013 às 17:21",
      "comment": "ccc",
      "type": "Comment",
      "user": {
        "is_editor": false,
        "picture": "http://www.xxx.yyy/4",
        "name": "kkkkkk"
      },
      "group": {
        "id": 2,
        "name": "pppppp"
      }
    },
    {
      "created_at": "21/11/2013 às 17:21",
      "comment": "ccc",
      "type": "Comment",
      "user": {
        "is_editor": false,
        "picture": "http://www.xxx.yyy/4",
        "name": "kkkkkk"
      },
      "group": {
        "id": 2,
        "name": "pppppp"
      }
    },
    {
      "created_at": "21/11/2013 às 17:21",
      "comment": "ccc",
      "type": "Comment",
      "user": {
        "is_editor": false,
        "picture": "http://www.xxx.yyy/4",
        "name": "kkkkkk"
      },
      "group": {
        "id": 2,
        "name": "pppppp"
      }
    },
    {
      "created_at": "21/11/2013 às 17:21",
      "comment": "ccc",
      "type": "Comment",
      "user": {
        "is_editor": false,
        "picture": "http://www.xxx.yyy/4",
        "name": "kkkkkk"
      },
      "group": {
        "id": 2,
        "name": "pppppp"
      }
    },
    {
      "created_at": "21/11/2013 às 17:21",
      "comment": "ccc",
      "type": "Comment",
      "user": {
        "is_editor": false,
        "picture": "http://www.xxx.yyy/4",
        "name": "kkkkkk"
      },
      "group": {
        "id": 2,
        "name": "pppppp"
      }
    },
    {
      "created_at": "21/11/2013 às 17:21",
      "comment": "ccc",
      "type": "Comment",
      "user": {
        "is_editor": false,
        "picture": "http://www.xxx.yyy/4",
        "name": "kkkkkk"
      },
      "group": {
        "id": 2,
        "name": "pppppp"
      }
    },
    {
      "created_at": "21/11/2013 às 17:21",
      "comment": "ccc",
      "type": "Comment",
      "user": {
        "is_editor": false,
        "picture": "http://www.xxx.yyy/4",
        "name": "kkkkkk"
      },
      "group": {
        "id": 2,
        "name": "pppppp"
      }
    },
    {
      "created_at": "21/11/2013 às 17:21",
      "comment": "ccc",
      "type": "Comment",
      "user": {
        "is_editor": false,
        "picture": "http://www.xxx.yyy/4",
        "name": "kkkkkk"
      },
      "group": {
        "id": 2,
        "name": "pppppp"
      }
    },
    {
      "created_at": "21/11/2013 às 17:21",
      "comment": "ccc",
      "type": "Comment",
      "user": {
        "is_editor": false,
        "picture": "http://www.xxx.yyy/4",
        "name": "kkkkkk"
      },
      "group": {
        "id": 2,
        "name": "pppppp"
      }
    },
    {
      "created_at": "21/11/2013 às 17:21",
      "comment": "ccc",
      "type": "Comment",
      "user": {
        "is_editor": false,
        "picture": "http://www.xxx.yyy/4",
        "name": "kkkkkk"
      },
      "group": {
        "id": 2,
        "name": "pppppp"
      }
    },
    {
      "created_at": "21/11/2013 às 17:21",
      "comment": "ccc",
      "type": "Comment",
      "user": {
        "is_editor": false,
        "picture": "http://www.xxx.yyy/4",
        "name": "kkkkkk"
      },
      "group": {
        "id": 2,
        "name": "pppppp"
      }
    },
    {
      "created_at": "21/11/2013 às 17:21",
      "comment": "ccc",
      "type": "Comment",
      "user": {
        "is_editor": false,
        "picture": "http://www.xxx.yyy/4",
        "name": "kkkkkk"
      },
      "group": {
        "id": 2,
        "name": "pppppp"
      }
    },
    {
      "created_at": "21/11/2013 às 17:21",
      "comment": "ccc",
      "type": "Comment",
      "user": {
        "is_editor": false,
        "picture": "http://www.xxx.yyy/4",
        "name": "kkkkkk"
      },
      "group": {
        "id": 2,
        "name": "pppppp"
      }
    },
    {
      "created_at": "21/11/2013 às 17:21",
      "comment": "ccc",
      "type": "Comment",
      "user": {
        "is_editor": false,
        "picture": "http://www.xxx.yyy/4",
        "name": "kkkkkk"
      },
      "group": {
        "id": 2,
        "name": "pppppp"
      }
    },
    {
      "created_at": "21/11/2013 às 17:21",
      "comment": "ccc",
      "type": "Comment",
      "user": {
        "is_editor": false,
        "picture": "http://www.xxx.yyy/4",
        "name": "kkkkkk"
      },
      "group": {
        "id": 2,
        "name": "pppppp"
      }
    }
  ],
  "status": "used"
}